x_django_app/APIViews.py
x_django_app/__init__.py
x_django_app/apps.py
x_django_app/forms.py
x_django_app/models.py
x_django_app/views.py
x_django_app/locale/ar/LC_MESSAGES/django.mo
x_django_app/locale/ar/LC_MESSAGES/django.po
x_django_app/migrations/__init__.py
x_django_app/templates/x_django_app/_pagination.html
x_django_app/templatetags/__init__.py
x_django_app/templatetags/x_tags.py
x_django_app-1.2.2.dist-info/LICENSE
x_django_app-1.2.2.dist-info/METADATA
x_django_app-1.2.2.dist-info/WHEEL
x_django_app-1.2.2.dist-info/top_level.txt
x_django_app-1.2.2.dist-info/RECORD
