Metadata-Version: 2.1
Name: x-django-app
Version: 1.2.2
Summary: A Python package to get weather reports for any location.
Home-page: https://github.com/XecusM/x-django-app
Author: Mohamed Aboel-fotouh
Author-email: abo.elfotouh@live.com
License: MIT
Classifier: License :: OSI Approved :: MIT License
Classifier: Programming Language :: Python :: 3
Classifier: Programming Language :: Python :: 3.8
License-File: LICENSE
Requires-Dist: django
Requires-Dist: djangorestframework
Requires-Dist: langdetect
